{
	"ai": {
		"ai": "186b2af5-1f9b-464e-ad9b-725724b2029awwww",
		"an": "iOSDemoSession",
		"av": "555",
		"ci": "appstor",
        "at": 2
	},
	"cmt": 1635499850259221,
	"di": {
		"a": "111",
		"bn": "apple",
		"ch": "apple",
		"ci": "arm64",
		"cm": "arm64",
		"di": "013A99CF-BA24-468F-A290-7EABD26EAA7C",
		"ds": "1125*2436",
		"l": "zh-Hans-AR",
		"m": "andorid14,1",
		"obv": "19A346",
		"omv": "iOS 15.0",
		"ot": 0,
		"ram": 6144,
		"rom": 51200
	},
	"ds": {
		"16987467829644A7F28CC-F4F6-4434-87A5-2912568972FA": {
			"auc": 20,
			"aura": 3072,
			"ot": 1,
			"s": 0,
			"sab": 95,
			"sara": 3072,
			"saro": 10240,
			"suc": 20
		}
	},
	"e": [
      {
      "ent" : 1698746783039536,
      "k" : "network",
      "sin" : [
        "",
        "16987467829644A7F28CC-F4F6-4434-87A5-2912568972FA",
        "a4e23cd6d2c288966aa77f3dafeaef30"
      ],
      "v" : {
        "art" : 10,
        "ct" : 12000,
        "ds" : 21,
        "dt" : 0,
        "dti" : 999,
        "ec" : 200,
        "ic" : false,
        "id" : "88CB741D-481D-45C3-BF16-EC9C579E3BC1",
        "m" : "POST",
        "pt" : 1,
        "rds" : 0,
        "ret" : "text/plain;charset=UTF-8",
        "rt" : 999,
        "rti" : 12976,
        "ru" : "http://10.241.131.14:9999/grip?v=2023092101&a=c78cdb0c-3eb7-4551-939f-62eb17426cda&d=5FD9A29A-5C93-4AB3-ADED-C1FC5E603304",
        "sslt" : 0,
        "ti" : "10.241.131.14",
        "tp" : 9999
      }
    },
    {
      "ent" : 1698746783018166,
      "k" : "network",
      "sin" : [
        "",
        "16987467829644A7F28CC-F4F6-4434-87A5-2912568972FA",
        "a4e23cd6d2c288966aa77f3dafeaef30"
      ],
      "v" : {
        "art" : 10,
        "ct" : 16999,
        "ds" : 363,
        "dt" : 1000,
        "dti" : 999,
        "ec" : 200,
        "ic" : false,
        "id" : "8B24AA45-6FE1-437F-B54C-88C0E73B642D",
        "m" : "POST",
        "pt" : 1,
        "rds" : 267,
        "ret" : "text/plain;charset=UTF-8",
        "rt" : 2373,
        "rti" : 29642,
        "ru" : "http://demtest.bonree.com/gonghangrnconfig?v=2023092101&a=c78cdb0c-3eb7-4551-939f-62eb17426cda&d=5FD9A29A-5C93-4AB3-ADED-C1FC5E603304",
        "sslt" : 0,
        "ti" : "120.133.67.137",
        "tp" : 80
      }
    },
    {
      "ent" : 1698746783061214,
      "k" : "network",
      "sin" : [
        "",
        "16987467829644A7F28CC-F4F6-4434-87A5-2912568972FA",
        "a4e23cd6d2c288966aa77f3dafeaef30"
      ],
      "v" : {
        "art" : 10,
        "ct" : 52000,
        "ds" : 23,
        "dt" : 0,
        "dti" : 999,
        "ec" : 200,
        "ic" : false,
        "id" : "C246575D-003A-4A2B-85E6-65DA68366D5F",
        "m" : "GET",
        "pt" : 1,
        "rds" : 0,
        "rt" : 999,
        "rti" : 15759,
        "ru" : "http://192.168.31.59:8081/status",
        "sslt" : 0,
        "ti" : "192.168.31.59",
        "tp" : 8081
      }
    },
    {
      "ent" : 1698746786208486,
      "k" : "network",
      "sin" : [
        "",
        "16987467829644A7F28CC-F4F6-4434-87A5-2912568972FA",
        "a4e23cd6d2c288966aa77f3dafeaef30"
      ],
      "v" : {
        "art" : 10,
        "ct" : 16000,
        "ds" : 761,
        "dt" : 0,
        "dti" : 999,
        "ec" : 200,
        "ic" : false,
        "id" : "534FA529-336A-4862-994E-E2A7528686A9",
        "m" : "GET",
        "pt" : 1,
        "rds" : 0,
        "ret" : "image/png",
        "rt" : 999,
        "rti" : 20695,
        "ru" : "http://192.168.31.59:8081/assets/node_modules/react-navigation-stack/dist/views/assets/back-icon@3x.png?platform=ios&hash=c90fb4585dd852a3d67af39baf923f67",
        "sslt" : 0,
        "ti" : "192.168.31.59",
        "tp" : 8081
      }
    },
    {
      "ent" : 1698746783192725,
      "k" : "view",
      "sin" : [
        "",
        "16987467829644A7F28CC-F4F6-4434-87A5-2912568972FA",
        "0c3cdcc43eb41b15dec71b8c1d05c475"
      ],
      "v" : {
        "ci" : "717D7401-D657-41EE-AD0C-4A04A0A945A9",
        "ic" : false,
        "is" : false,
        "lt" : 9779,
        "m" : 1,
        "n" : "OneViewController",
        "t" : 5
      }
    },
    {
      "ent" : 1698746784199000,
      "k" : "view",
      "sin" : [
        "",
        "16987467829644A7F28CC-F4F6-4434-87A5-2912568972FA",
        "a4e23cd6d2c288966aa77f3dafeaef30"
      ],
      "v" : {
        "ci" : "0D46D195-E408-4F1F-9F5B-26D677F406A4",
        "ic" : false,
        "is" : false,
        "lt" : 30000,
        "m" : 1,
        "n" : "Home",
        "t" : 6
      }
    },
    {
      "ent" : 1698746786965000,
      "k" : "view",
      "sin" : [
        "",
        "16987467829644A7F28CC-F4F6-4434-87A5-2912568972FA",
        "a4e23cd6d2c288966aa77f3dafeaef30"
      ],
      "v" : {
        "ci" : "0D46D195-E408-4F1F-9F5B-26D677F406A4",
        "ic" : false,
        "is" : false,
        "lt" : 30000,
        "m" : 2,
        "n" : "Home",
        "st" : 2766000,
        "t" : 6
      }
    },
    {
      "ent" : 1698746786970000,
      "k" : "view",
      "sin" : [
        "",
        "16987467829644A7F28CC-F4F6-4434-87A5-2912568972FA",
        "a4e23cd6d2c288966aa77f3dafeaef30"
      ],
      "v" : {
        "ci" : "ACACB58E-7DC1-40EB-9F69-8C4CC745105C",
        "ic" : false,
        "is" : false,
        "lt" : 21000,
        "m" : 1,
        "n" : "Detail111",
        "t" : 6
      }
    },
    {
      "ent" : 1698746789888000,
      "k" : "view",
      "sin" : [
        "",
        "16987467829644A7F28CC-F4F6-4434-87A5-2912568972FA",
        "a4e23cd6d2c288966aa77f3dafeaef30"
      ],
      "v" : {
        "ci" : "ACACB58E-7DC1-40EB-9F69-8C4CC745105C",
        "ic" : false,
        "is" : false,
        "lt" : 21000,
        "m" : 2,
        "n" : "Detail111",
        "st" : 2918000,
        "t" : 6
      }
    },
    {
      "ent" : 1698746789891000,
      "k" : "view",
      "sin" : [
        "",
        "16987467829644A7F28CC-F4F6-4434-87A5-2912568972FA",
        "a4e23cd6d2c288966aa77f3dafeaef30"
      ],
      "v" : {
        "ci" : "ACBF4B37-C17C-42A6-9061-DF99C6821606",
        "ic" : false,
        "is" : false,
        "lt" : 999,
        "m" : 1,
        "n" : "Home",
        "t" : 6
      }
    },
    {
      "ent" : 1698746791615000,
      "k" : "view",
      "sin" : [
        "",
        "16987467829644A7F28CC-F4F6-4434-87A5-2912568972FA",
        "a4e23cd6d2c288966aa77f3dafeaef30"
      ],
      "v" : {
        "ci" : "9A46EAEA-80F6-4E51-99F7-E4186B154C82",
        "ic" : false,
        "is" : false,
        "lt" : 26000,
        "m" : 1,
        "n" : "Detail111",
        "t" : 6
      }
    },
    {
      "ent" : 1698746792585000,
      "k" : "view",
      "sin" : [
        "",
        "16987467829644A7F28CC-F4F6-4434-87A5-2912568972FA",
        "a4e23cd6d2c288966aa77f3dafeaef30"
      ],
      "v" : {
        "ci" : "9A46EAEA-80F6-4E51-99F7-E4186B154C82",
        "ic" : false,
        "is" : false,
        "lt" : 26000,
        "m" : 2,
        "n" : "Detail111",
        "st" : 970000,
        "t" : 6
      }
    },
    {
      "ent" : 1698746792590000,
      "k" : "view",
      "sin" : [
        "",
        "16987467829644A7F28CC-F4F6-4434-87A5-2912568972FA",
        "a4e23cd6d2c288966aa77f3dafeaef30"
      ],
      "v" : {
        "ci" : "AFCABA6A-3C83-49C0-B6B3-00B06395CB55",
        "ic" : false,
        "is" : false,
        "lt" : 999,
        "m" : 1,
        "n" : "Home",
        "t" : 6
      }
    },
    {
      "ent" : 1698746793704000,
      "k" : "view",
      "sin" : [
        "",
        "16987467829644A7F28CC-F4F6-4434-87A5-2912568972FA",
        "a4e23cd6d2c288966aa77f3dafeaef30"
      ],
      "v" : {
        "ci" : "E9102D0C-6054-47E3-9E25-E467ADBB6521",
        "ic" : false,
        "is" : false,
        "lt" : 34000,
        "m" : 1,
        "n" : "Detail111",
        "t" : 6
      }
    },
    {
      "ent" : 1698746794281000,
      "k" : "view",
      "sin" : [
        "",
        "16987467829644A7F28CC-F4F6-4434-87A5-2912568972FA",
        "a4e23cd6d2c288966aa77f3dafeaef30"
      ],
      "v" : {
        "ci" : "E9102D0C-6054-47E3-9E25-E467ADBB6521",
        "ic" : false,
        "is" : false,
        "lt" : 34000,
        "m" : 2,
        "n" : "Detail111",
        "st" : 577000,
        "t" : 6
      }
    },
    {
      "ent" : 1698746794287000,
      "k" : "view",
      "sin" : [
        "",
        "16987467829644A7F28CC-F4F6-4434-87A5-2912568972FA",
        "a4e23cd6d2c288966aa77f3dafeaef30"
      ],
      "v" : {
        "ci" : "E9CA6847-8CB7-49C7-B789-2E779AC8D2FC",
        "ic" : false,
        "is" : false,
        "lt" : 999,
        "m" : 1,
        "n" : "Home",
        "t" : 6
      }
    },
    {
      "ent" : 1698746796235196,
      "k" : "view",
      "sin" : [
        "",
        "16987467829644A7F28CC-F4F6-4434-87A5-2912568972FA",
        "a4e23cd6d2c288966aa77f3dafeaef30"
      ],
      "v" : {
        "ci" : "E9CA6847-8CB7-49C7-B789-2E779AC8D2FC",
        "ic" : false,
        "is" : false,
        "lt" : 999,
        "m" : 2,
        "n" : "Home",
        "st" : 1948196,
        "t" : 6
      }
    },
    {
      "ent" : 1698746796235196,
      "k" : "view",
      "sin" : [
        "",
        "16987467829644A7F28CC-F4F6-4434-87A5-2912568972FA",
        "a4e23cd6d2c288966aa77f3dafeaef30"
      ],
      "v" : {
        "ci" : "AFCABA6A-3C83-49C0-B6B3-00B06395CB55",
        "ic" : false,
        "is" : false,
        "lt" : 999,
        "m" : 2,
        "n" : "Home",
        "st" : 3645196,
        "t" : 6
      }
    },
    {
      "ent" : 1698746796235196,
      "k" : "view",
      "sin" : [
        "",
        "16987467829644A7F28CC-F4F6-4434-87A5-2912568972FA",
        "a4e23cd6d2c288966aa77f3dafeaef30"
      ],
      "v" : {
        "ci" : "ACBF4B37-C17C-42A6-9061-DF99C6821606",
        "ic" : false,
        "is" : false,
        "lt" : 999,
        "m" : 2,
        "n" : "Home",
        "st" : 6344196,
        "t" : 6
      }
    },
    {
      "ent" : 1698746796235196,
      "k" : "view",
      "sin" : [
        "",
        "16987467829644A7F28CC-F4F6-4434-87A5-2912568972FA",
        "a4e23cd6d2c288966aa77f3dafeaef30"
      ],
      "v" : {
        "ci" : "717D7401-D657-41EE-AD0C-4A04A0A945A9",
        "ic" : false,
        "is" : false,
        "lt" : 9779,
        "m" : 2,
        "n" : "OneViewController",
        "st" : 13032692,
        "t" : 5
      }
    },
    {
      "ent" : 1698746786138000,
      "k" : "action",
      "sin" : [
        "",
        "16987467829644A7F28CC-F4F6-4434-87A5-2912568972FA",
        "a4e23cd6d2c288966aa77f3dafeaef30"
      ],
      "v" : {
        "fer" : 0,
        "i" : "Home Bundle go to detail1111",
        "ic" : false,
        "is" : false,
        "lt" : 8000,
        "n" : "Button",
        "sa" : 2,
        "t" : 1,
        "vn" : "Home",
        "vt" : 6
      }
    },
    {
      "ent" : 1698746790758000,
      "k" : "action",
      "sin" : [
        "",
        "16987467829644A7F28CC-F4F6-4434-87A5-2912568972FA",
        "a4e23cd6d2c288966aa77f3dafeaef30"
      ],
      "v" : {
        "fer" : 0,
        "i" : "Home Bundle go to detail1111",
        "ic" : false,
        "is" : false,
        "lt" : 17000,
        "n" : "Button",
        "sa" : 2,
        "t" : 1,
        "vn" : "DetailScreen",
        "vt" : 6
      }
    },
    {
      "ent" : 1698746792850000,
      "k" : "action",
      "sin" : [
        "",
        "16987467829644A7F28CC-F4F6-4434-87A5-2912568972FA",
        "a4e23cd6d2c288966aa77f3dafeaef30"
      ],
      "v" : {
        "fer" : 0,
        "i" : "Home Bundle go to detail1111",
        "ic" : false,
        "is" : false,
        "lt" : 15000,
        "n" : "Button",
        "sa" : 2,
        "t" : 1,
        "vn" : "DetailScreen",
        "vt" : 6
      }
    },
    {
      "ent" : 1698746796234319,
      "k" : "statechange",
      "sin" : [
        "",
        "16987467829644A7F28CC-F4F6-4434-87A5-2912568972FA",
        "a4e23cd6d2c288966aa77f3dafeaef30"
      ],
      "v" : {
        "t" : 3
      }
    },
    {
      "ent" : 1698746782877343,
      "k" : "launch",
      "sin" : [
        "",
        "16987467829644A7F28CC-F4F6-4434-87A5-2912568972FA",
        "0c3cdcc43eb41b15dec71b8c1d05c475"
      ],
      "v" : {
        "is" : false,
        "lt" : 325161,
        "t" : 1
      }
    },
    {
      "ent" : 1698746783058097,
      "k" : "rnload",
      "sin" : [
        "",
        "16987467829644A7F28CC-F4F6-4434-87A5-2912568972FA",
        "a4e23cd6d2c288966aa77f3dafeaef30"
      ],
      "v" : {
        "bn" : "Page1",
        "id" : "48FB6C99-6A32-4C64-8947-9B6AEC91D8D4",
        "jslt" : 889,
        "rt" : 0,
        "t" : 1,
        "tti" : 1151538
      }
    },
    {
      "ent" : 1698746786970,
      "k" : "rnload",
      "sin" : [
        "",
        "16987467829644A7F28CC-F4F6-4434-87A5-2912568972FA",
        "a4e23cd6d2c288966aa77f3dafeaef30"
      ],
      "v" : {
        "bn" : "Page1",
        "id" : "id-1698746784084-1",
        "jslt" : 0,
        "rn" : "Detail111",
        "rt" : 21,
        "t" : 2,
        "tti" : 0
      }
    },
    {
      "ent" : 1698746789891,
      "k" : "rnload",
      "sin" : [
        "",
        "16987467829644A7F28CC-F4F6-4434-87A5-2912568972FA",
        "a4e23cd6d2c288966aa77f3dafeaef30"
      ],
      "v" : {
        "bn" : "Page1",
        "id" : "id-1698746784084-0",
        "jslt" : 0,
        "rn" : "Home",
        "rt" : 0,
        "t" : 2,
        "tti" : 0
      }
    },
    {
      "ent" : 1698746791615,
      "k" : "rnload",
      "sin" : [
        "",
        "16987467829644A7F28CC-F4F6-4434-87A5-2912568972FA",
        "a4e23cd6d2c288966aa77f3dafeaef30"
      ],
      "v" : {
        "bn" : "Page1",
        "id" : "id-1698746784084-2",
        "jslt" : 0,
        "rn" : "Detail111",
        "rt" : 26,
        "t" : 2,
        "tti" : 0
      }
    },
    {
      "ent" : 1698746792590,
      "k" : "rnload",
      "sin" : [
        "",
        "16987467829644A7F28CC-F4F6-4434-87A5-2912568972FA",
        "a4e23cd6d2c288966aa77f3dafeaef30"
      ],
      "v" : {
        "bn" : "Page1",
        "id" : "id-1698746784084-0",
        "jslt" : 0,
        "rn" : "Home",
        "rt" : 0,
        "t" : 2,
        "tti" : 0
      }
    },
    {
      "ent" : 1698746793704,
      "k" : "rnload",
      "sin" : [
        "",
        "16987467829644A7F28CC-F4F6-4434-87A5-2912568972FA",
        "a4e23cd6d2c288966aa77f3dafeaef30"
      ],
      "v" : {
        "bn" : "Page1",
        "id" : "id-1698746784084-3",
        "jslt" : 0,
        "rn" : "Detail111",
        "rt" : 34,
        "t" : 2,
        "tti" : 0
      }
    },
    {
      "ent" : 1698746794287,
      "k" : "rnload",
      "sin" : [
        "",
        "16987467829644A7F28CC-F4F6-4434-87A5-2912568972FA",
        "a4e23cd6d2c288966aa77f3dafeaef30"
      ],
      "v" : {
        "bn" : "Page1",
        "id" : "id-1698746784084-0",
        "jslt" : 0,
        "rn" : "Home",
        "rt" : 0,
        "t" : 2,
        "tti" : 0
      }
    },
    {
      "ent" : 1698746783269828,
      "k" : "span",
      "sin" : [
        "",
        "16987467829644A7F28CC-F4F6-4434-87A5-2912568972FA",
        "a4e23cd6d2c288966aa77f3dafeaef30"
      ],
      "v" : {
        "da" : [

        ],
        "du" : 291,
        "ic" : false,
        "m" : [
          {
            "k" : "tcp",
            "u" : "us",
            "v" : 291
          }
        ],
        "n" : "0.0.0.0:80",
        "st" : 0,
        "sta" : 2,
        "stac" : "61",
        "sub" : [

        ],
        "t" : "socket",
        "tag" : [
          {
            "k" : "process",
            "v" : "connect"
          },
          {
            "k" : "connectID",
            "v" : "55AD7B5A-DCC1-4B5B-91E3-E439CB797D05"
          }
        ]
      }
    }
	],
	"mt": 1635499851634728,
	"nsi": {
		"a4e23cd6d2c288966aa77f3dafeaef30": {
			"dip": "38.165.61.171",
			"dsi": "192.250.12.48",
			"ns": "ctradioaccesstechnologynr"
		}
	},
	"ui": {
		"a570357e-8873-419f-b9f9-28804ce8acf5": {
			"ui": "yl",
			"ei": "{\"123博睿测试-userid（~！@#￥%……&*（）——+）\":\"博睿测试-688229（~！@#￥%……&*（）——+）\",\"博睿测试-userinfo（~！@#￥%……&*（）——+）\":\"ky2123214214（~！@#￥%……&*（）——+）\"}"
		}
	},
	"s": "eacc7e2e-dca5-42f7-8c10-16fd0d16f01c",
	"usd": 4,
	"v": "8.3.0"
}